{
    "coord": {
        "lon": 78.4744,
        "lat": 17.3753
    },
    "weather": [
        {
            "id": 721,
            "main": "Haze",
            "description": "haze",
            "icon": "50n"
        }
    ],
    "base": "stations",
    "main": {
        "temp": 54.91,
        "feels_like": 53.67,
        "temp_min": 54.91,
        "temp_max": 54.91,
        "pressure": 1015,
        "humidity": 76,
        "sea_level": 1015,
        "grnd_level": 951
    },
    "visibility": 4000,
    "wind": {
        "speed": 4.61,
        "deg": 0
    },
    "clouds": {
        "all": 33
    },
    "dt": 1765234403,
    "sys": {
        "type": 1,
        "id": 9213,
        "country": "IN",
        "sunrise": 1765242298,
        "sunset": 1765282325
    },
    "timezone": 19800,
    "id": 1269843,
    "name": "Hyderabad",
    "cod": 200
}